pokewrap/__init__.py
pokewrap/api.py
pokewrap/wrappers.py
pokewrap-1.0.8.dist-info/LICENSE
pokewrap-1.0.8.dist-info/METADATA
pokewrap-1.0.8.dist-info/WHEEL
pokewrap-1.0.8.dist-info/top_level.txt
pokewrap-1.0.8.dist-info/RECORD
