Metadata-Version: 2.1
Name: pokewrap
Version: 1.0.8
Summary: A wrapper library for the PokeAPI making it easier to retrieve and use data from the API endpoint.
Home-page: https://github.com/jasongarvin/pokewrap
Author: Jason Garvin
Author-email: Jason Garvin <jsongarvin@gmail.com>
License: # MIT License
Project-URL: Homepage, https://github.com/jasongarvin/pokewrap
Keywords: feed,reader,tutorial
Classifier: License :: OSI Approved :: MIT License
Classifier: Programming Language :: Python
Classifier: Programming Language :: Python :: 3
Requires-Python: >=3.9
License-File: LICENSE
Requires-Dist: requests
Provides-Extra: dev
Requires-Dist: pytest ; extra == 'dev'
Requires-Dist: pip-tools ; extra == 'dev'
